pyxero-0.9.5.dist-info/licenses/LICENSE
xero/__init__.py
xero/api.py
xero/auth.py
xero/basemanager.py
xero/constants.py
xero/exceptions.py
xero/filesmanager.py
xero/manager.py
xero/paymentmanager.py
xero/payrollmanager.py
xero/projectmanager.py
xero/utils.py
pyxero-0.9.5.dist-info/METADATA
pyxero-0.9.5.dist-info/WHEEL
pyxero-0.9.5.dist-info/top_level.txt
pyxero-0.9.5.dist-info/RECORD
