Metadata-Version: 2.4
Name: pyxero
Version: 0.9.5
Summary: Python API for accessing the REST API of the Xero accounting tool.
Author-email: Russell Keith-Magee <russell@keith-magee.com>
Maintainer-email: Russell Keith-Magee <russell@keith-magee.com>
License-Expression: BSD-3-Clause
Project-URL: Homepage, https://github.com/freakboy3742/pyxero
Project-URL: Tracker, https://github.com/freakboy3742/pyxero/issues
Project-URL: Source, https://github.com/freakboy3742/pyxero
Keywords: xero,api
Classifier: Development Status :: 4 - Beta
Classifier: Environment :: Web Environment
Classifier: Intended Audience :: Financial and Insurance Industry
Classifier: Operating System :: OS Independent
Classifier: Programming Language :: Python
Classifier: Programming Language :: Python :: 3.9
Classifier: Programming Language :: Python :: 3.10
Classifier: Programming Language :: Python :: 3.11
Classifier: Programming Language :: Python :: 3.12
Classifier: Programming Language :: Python :: 3.13
Classifier: Programming Language :: Python :: 3.14
Classifier: Topic :: Office/Business :: Financial :: Accounting
Requires-Python: >=3.9
License-File: LICENSE
Requires-Dist: requests<3,>=1.1.0
Requires-Dist: requests-oauthlib<3,>=0.3.0
Requires-Dist: python-dateutil<3,>=2.8
Requires-Dist: PyJWT<3,>=1.6.4
Requires-Dist: cryptography>=1.3.1
Provides-Extra: dev
Requires-Dist: pre-commit==4.2.0; extra == "dev"
Requires-Dist: pytest==8.3.5; extra == "dev"
Requires-Dist: tox==4.26.0; extra == "dev"
Dynamic: license-file
